glitter_sdk_lite/.gitignore
glitter_sdk_lite/__init__.py
glitter_sdk_lite/client/__init__.py
glitter_sdk_lite/client/lcd/__init__.py
glitter_sdk_lite/client/lcd/db.py
glitter_sdk_lite/client/lcd/lcdclient.py
glitter_sdk_lite/core/__init__.py
glitter_sdk_lite/core/bech32.py
glitter_sdk_lite/core/msg.py
glitter_sdk_lite/core/msgs/__init__.py
glitter_sdk_lite/core/msgs/argument.py
glitter_sdk_lite/core/msgs/arguments.py
glitter_sdk_lite/core/msgs/msgs.py
glitter_sdk_lite/exceptions.py
glitter_sdk_lite/util/__init__.py
glitter_sdk_lite/util/base.py
glitter_sdk_lite/util/constants/CLIENT.py
glitter_sdk_lite/util/constants/COMMAND.py
glitter_sdk_lite/util/constants/CR.py
glitter_sdk_lite/util/constants/ER.py
glitter_sdk_lite/util/constants/FIELD_TYPE.py
glitter_sdk_lite/util/constants/FLAG.py
glitter_sdk_lite/util/constants/SERVER_STATUS.py
glitter_sdk_lite/util/constants/__init__.py
glitter_sdk_lite/util/contract.py
glitter_sdk_lite/util/converter.py
glitter_sdk_lite/util/hash.py
glitter_sdk_lite/util/highlight.py
glitter_sdk_lite/util/json.py
glitter_sdk_lite/util/parse_authorization.py
glitter_sdk_lite/util/parse_content.py
glitter_sdk_lite/util/parse_msg.py
glitter_sdk_lite/util/parse_proto.py
glitter_sdk_lite/util/parse_query_str.py
glitter_sdk_lite/util/parse_sql.py
glitter_sdk_lite/util/remove_none.py
glitter_sdk_lite/util/url.py
glitter_sdk_lite-0.0.3.dist-info/LICENSE
glitter_sdk_lite-0.0.3.dist-info/METADATA
glitter_sdk_lite-0.0.3.dist-info/WHEEL
glitter_sdk_lite-0.0.3.dist-info/RECORD
