Metadata-Version: 2.1
Name: glitter-sdk-lite
Version: 0.0.3
Summary: glitter-sdk-lite is a lite SDK for accessing the glitter network.
Author: Glitter Protocol
Author-email: ted@glitterprotocol.io
Requires-Python: >=3.7,<4.0
Classifier: Programming Language :: Python :: 3
Classifier: Programming Language :: Python :: 3.7
Classifier: Programming Language :: Python :: 3.8
Classifier: Programming Language :: Python :: 3.9
Classifier: Programming Language :: Python :: 3.10
Classifier: Programming Language :: Python :: 3.11
Requires-Dist: bech32 (>=1.2.0,<2.0.0)
Requires-Dist: betterproto (==2.0.0b4)
Requires-Dist: furl (>=2.1.3,<3.0.0)
Requires-Dist: glitter-proto (==0.6.0)
Requires-Dist: requests (>=2.31.0,<3.0.0)
